radix_tree/__about__.py
radix_tree/__init__.py
radix_tree/__main__.py
radix_tree/radix_config.py
radix_tree/radix_tree.py
radix_tree/.idea/.gitignore
radix_tree/.idea/misc.xml
radix_tree/.idea/modules.xml
radix_tree/.idea/radix_tree.iml
radix_tree/.idea/vcs.xml
radix_tree/.idea/workspace.xml
radix_tree/.idea/inspectionProfiles/profiles_settings.xml
radix_tree-0.0.3.dist-info/METADATA
radix_tree-0.0.3.dist-info/WHEEL
radix_tree-0.0.3.dist-info/licenses/LICENSE.txt
radix_tree-0.0.3.dist-info/RECORD
