Metadata-Version: 2.3
Name: radix_tree
Version: 0.0.3
Summary: Generic pure python radix tree implementation
Project-URL: Documentation, https://github.com/Nicola-31/radix-tree#readme
Project-URL: Issues, https://github.com/Nicola-31/radix-tree/issues
Project-URL: Source, https://github.com/Nicola-31/radix-tree
Author-email: Nicolas Jeudy <nicola.jeudy@gmail.com>
License-Expression: MIT
License-File: LICENSE.txt
Keywords: radix,tree
Classifier: Development Status :: 4 - Beta
Classifier: Programming Language :: Python
Classifier: Programming Language :: Python :: 3.5
Classifier: Programming Language :: Python :: 3.6
Classifier: Programming Language :: Python :: 3.7
Classifier: Programming Language :: Python :: 3.8
Classifier: Programming Language :: Python :: 3.9
Classifier: Programming Language :: Python :: 3.10
Classifier: Programming Language :: Python :: 3.11
Classifier: Programming Language :: Python :: 3.12
Classifier: Programming Language :: Python :: Implementation :: CPython
Classifier: Programming Language :: Python :: Implementation :: PyPy
Requires-Python: >=3.5
